kademlia/__init__.py
kademlia/crawling.py
kademlia/network.py
kademlia/node.py
kademlia/protocol.py
kademlia/routing.py
kademlia/storage.py
kademlia/utils.py
kademlia/tests/__init__.py
kademlia/tests/conftest.py
kademlia/tests/test_linting.py
kademlia/tests/test_node.py
kademlia/tests/test_routing.py
kademlia/tests/test_server.py
kademlia/tests/test_storage.py
kademlia/tests/test_utils.py
kademlia-2.2.2.dist-info/LICENSE
kademlia-2.2.2.dist-info/METADATA
kademlia-2.2.2.dist-info/WHEEL
kademlia-2.2.2.dist-info/top_level.txt
kademlia-2.2.2.dist-info/RECORD
